{"score_history":{"GRPN":[["29.04.2026",62.11],["30.04.2026",60.7],["12.05.2026",66.84]],"INDI":[["29.04.2026",73.39],["30.04.2026",80.23]],"XRX":[["29.04.2026",40.69],["30.04.2026",88.96]],"AVTX":[["29.04.2026",36.51]],"AMC":[["29.04.2026",16.14],["30.04.2026",19.03]],"PRLD":[["30.04.2026",54.67]],"SNSE":[["29.04.2026",55.33],["30.04.2026",52.7],["12.05.2026",61.43],["13.05.2026",54.47]],"NTLA":[["29.04.2026",79.53],["30.04.2026",76.38]],"KALV":[["29.04.2026",100.0],["30.04.2026",100.0]],"RXRX":[["29.04.2026",49.63],["30.04.2026",64.51]],"SPRY":[["29.04.2026",58.24]],"PCT":[["29.04.2026",60.92],["30.04.2026",70.98]],"ENVX":[["29.04.2026",44.02],["30.04.2026",44.02]],"JACK":[["12.05.2026",51.23]],"ARCT":[["29.04.2026",70.37],["30.04.2026",54.14]],"SKLZ":[["30.04.2026",85.61]],"ACDC":[["29.04.2026",47.35],["30.04.2026",48.23]],"CWH":[["29.04.2026",18.48],["30.04.2026",57.5]],"VITL":[["30.04.2026",63.41]],"CBRL":[["29.04.2026",43.43],["30.04.2026",47.33]],"LENZ":[["29.04.2026",51.97],["30.04.2026",56.8]],"FTRE":[["30.04.2026",60.31]],"SNBR":[["29.04.2026",41.44],["30.04.2026",33.73]],"LGIH":[["29.04.2026",73.18]],"RIGL":[["12.05.2026",86.48],["13.05.2026",52.22]],"BBAI":[["29.04.2026",62.05]],"CSIQ":[["29.04.2026",50.36],["13.05.2026",48.78]],"MNPR":[["29.04.2026",55.45],["30.04.2026",57.33]],"SKYQ":[["29.04.2026",54.44],["30.04.2026",56.96]],"PRTA":[["29.04.2026",52.27]],"COUR":[["29.04.2026",47.52]],"ABEO":[["29.04.2026",43.72]],"AIXI":[["29.04.2026",41.99]],"PEB":[["29.04.2026",61.9]],"CLVT":[["29.04.2026",59.13],["30.04.2026",65.93]],"TRIP":[["29.04.2026",35.85],["30.04.2026",39.27]],"AI":[["29.04.2026",34.49]],"GCTK":[["29.04.2026",70.21]],"IQ":[["29.04.2026",44.73]],"NAVI":[["29.04.2026",67.75]],"FIP":[["30.04.2026",81.36]],"PRKS":[["30.04.2026",65.26]],"QURE":[["30.04.2026",65.13],["12.05.2026",50.89],["13.05.2026",52.44]],"SVRA":[["30.04.2026",50.47]],"WEN":[["12.05.2026",88.07],["13.05.2026",90.07]],"DDD":[["12.05.2026",85.8],["13.05.2026",50.51]],"METC":[["12.05.2026",90.73],["13.05.2026",94.29]],"FABC":[["12.05.2026",75.29]],"AEVA":[["12.05.2026",75.88],["13.05.2026",78.23]],"NVAX":[["12.05.2026",58.85]],"XPOF":[["12.05.2026",55.8]],"GO":[["12.05.2026",53.73],["13.05.2026",46.42]],"REPL":[["12.05.2026",54.13]],"CGEM":[["12.05.2026",69.05],["13.05.2026",72.85]],"ENOV":[["12.05.2026",57.48],["13.05.2026",64.57]],"RXT":[["12.05.2026",54.08],["13.05.2026",54.93]],"NVRI":[["12.05.2026",47.45],["13.05.2026",50.29]],"SLS":[["13.05.2026",68.59]],"HUMA":[["13.05.2026",55.37]],"CCCC":[["13.05.2026",54.97]],"TTEC":[["13.05.2026",51.77]],"DMRC":[["13.05.2026",48.65]]},"agent_signals":{"updated":"2026-05-13T18:17:27.568855+02:00","run_info":{"tickers_checked":10,"signals_active":0,"alerts_sent":0,"elapsed_s":30.6,"market_phase":"Regul\u00e4r"},"signals":{"SLS":{"score":55,"confidence":70,"drivers":"Volumen 3.1\u00d7 + \u26a1 Extremes Volumen 3.1\u00d7+ + Spanne 16.4% + UOA Call/Put 9.9\u00d7","price":5.74,"chg_pct":-0.0,"rvol":3.14,"earnings":"in 90 Tagen (11.08.2026)","fda_date":null,"upcoming_event":null,"insider_buy":false,"stocktwits":null,"combo_mult":1.0,"active_triggers":1,"uoa_score":10,"uoa_drivers":["UOA Call/Put 9.9\u00d7"],"uoa_atm_ratio":0.45297253797404685,"uoa_cp_ratio":9.872844827586206},"HUMA":{"score":91,"confidence":70,"drivers":"Earnings in 0 Tagen (13.05.2026) + Volumen 2.2\u00d7 + Spanne 34.6% + News-KI 8/30: Negative earnings miss with revenue underperformance signals weak fundamentals and limited short-squeeze potential despi + Earnings in 0d + FINRA Short-Vol 68% + UOA Call/Put 2.9\u00d7","price":1.09,"chg_pct":-0.46,"rvol":2.23,"earnings":"in 0 Tagen (13.05.2026)","fda_date":null,"upcoming_event":"Earnings in 0 Tagen (13.05.2026)","insider_buy":false,"stocktwits":null,"combo_mult":1.1,"active_triggers":2,"uoa_score":10,"uoa_drivers":["UOA Call/Put 2.9\u00d7"],"uoa_atm_ratio":0.7365421152628245,"uoa_cp_ratio":2.924019607843137},"CCCC":{"score":40,"confidence":70,"drivers":"Volumen 3.0\u00d7 + Spanne 25.7% + News-KI 5/30: Negative earnings miss with revenue lag indicates weak fundamentals and declining investor confidence, making this unsui + UOA Call/Put 10.0\u00d7","price":3.87,"chg_pct":-0.13,"rvol":2.98,"earnings":"in 85 Tagen (06.08.2026)","fda_date":null,"upcoming_event":null,"insider_buy":false,"stocktwits":null,"combo_mult":1.0,"active_triggers":1,"uoa_score":10,"uoa_drivers":["UOA Call/Put 10.0\u00d7"],"uoa_atm_ratio":0.2958579881656805,"uoa_cp_ratio":10.0},"SNSE":{"score":37,"confidence":33,"drivers":"News-KI 12/30: Positive clinical progress and analyst recognition, but small biotech with low institutional short interest makes squeez + FINRA Short-Vol 80%","price":20.98,"chg_pct":-0.02,"rvol":0.52,"earnings":null,"fda_date":null,"upcoming_event":null,"insider_buy":false,"stocktwits":null,"combo_mult":1.0,"active_triggers":1,"uoa_score":0,"uoa_drivers":[],"uoa_atm_ratio":null,"uoa_cp_ratio":null},"TTEC":{"score":20,"confidence":33,"drivers":"Spanne 13.0% + UOA Call/Put 56.0\u00d7","price":2.65,"chg_pct":0.0,"rvol":0.6,"earnings":"in 85 Tagen (06.08.2026)","fda_date":null,"upcoming_event":null,"insider_buy":false,"stocktwits":null,"combo_mult":1.0,"active_triggers":0,"uoa_score":10,"uoa_drivers":["UOA Call/Put 56.0\u00d7"],"uoa_atm_ratio":0.9554140127388535,"uoa_cp_ratio":56.0},"DDD":{"score":35,"confidence":33,"drivers":"Spanne 7.9% + News: earnings beat + UOA Call/Put 2.8\u00d7","price":3.13,"chg_pct":0.0,"rvol":0.42,"earnings":"in 89 Tagen (10.08.2026)","fda_date":null,"upcoming_event":null,"insider_buy":false,"stocktwits":null,"combo_mult":1.0,"active_triggers":1,"uoa_score":10,"uoa_drivers":["UOA Call/Put 2.8\u00d7"],"uoa_atm_ratio":0.08798681228106325,"uoa_cp_ratio":2.7953667953667956},"RIGL":{"score":40,"confidence":33,"drivers":"Spanne 11.1% + News: short interest, halt","price":31.84,"chg_pct":0.02,"rvol":0.76,"earnings":"in 83 Tagen (04.08.2026)","fda_date":null,"upcoming_event":null,"insider_buy":false,"stocktwits":null,"combo_mult":1.0,"active_triggers":1,"uoa_score":0,"uoa_drivers":[],"uoa_atm_ratio":0.3103448275862069,"uoa_cp_ratio":0.2237442922374429},"CSIQ":{"score":52,"confidence":70,"drivers":"Earnings in 1 Tagen (14.05.2026) + Spanne 6.5% + News-KI 12/30: Moderate rebound showing but no significant short interest indicators, contradictory signals with forecast losses offset + Earnings in 1d","price":20.23,"chg_pct":-0.0,"rvol":0.35,"earnings":"in 1 Tagen (14.05.2026)","fda_date":null,"upcoming_event":"Earnings in 1 Tagen (14.05.2026)","insider_buy":false,"stocktwits":null,"combo_mult":1.1,"active_triggers":2,"uoa_score":0,"uoa_drivers":[],"uoa_atm_ratio":0.1659462797159617,"uoa_cp_ratio":1.884507042253521},"DMRC":{"score":20,"confidence":33,"drivers":"Spanne 21.8% + UOA Call/Put 4.1\u00d7","price":9.65,"chg_pct":-0.0,"rvol":0.78,"earnings":null,"fda_date":null,"upcoming_event":null,"insider_buy":false,"stocktwits":null,"combo_mult":1.0,"active_triggers":0,"uoa_score":10,"uoa_drivers":["UOA Call/Put 4.1\u00d7"],"uoa_atm_ratio":0.16518424396442186,"uoa_cp_ratio":4.0588235294117645},"GO":{"score":53,"confidence":70,"drivers":"Earnings in 0 Tagen (13.05.2026) + Spanne 6.7% + News-KI 8/30: Negative earnings outlook with analyst downgrades suggests weakening momentum rather than short-squeeze potential; no in + Earnings in 0d + UOA Call/Put 12.5\u00d7","price":7.91,"chg_pct":-0.06,"rvol":0.61,"earnings":"in 0 Tagen (13.05.2026)","fda_date":null,"upcoming_event":"Earnings in 0 Tagen (13.05.2026)","insider_buy":false,"stocktwits":null,"combo_mult":1.0,"active_triggers":1,"uoa_score":10,"uoa_drivers":["UOA Call/Put 12.5\u00d7"],"uoa_atm_ratio":0.00032711808963035657,"uoa_cp_ratio":12.545454545454545}}},"watchlist_cards":{"DMRC":{"score":48.65,"monster_score":48.65,"ki_signal_score":null,"ki_signal_confidence":null,"ki_signal_drivers":null,"company_name":"Digimarc Corporation","sector":"Technology","flag":"\ud83c\uddfa\ud83c\uddf8","price":8.979999542236328,"change":0.79,"change_5d":9.78,"change_2d":0.34,"change_3d":-4.06,"spx_daily_perf":-0.10484809627340624,"short_float":30.68,"short_float_source":"yfinance","short_ratio":14.6,"rel_volume":0.43071490281467933,"rel_volume_yesterday":1.272,"float_shares":13895812,"si_trend":"sideways","si_trend_source":"yfinance","si_tpct":4.8,"si_velocity":-204.0,"si_accel":false,"si_t1":"71 Aktien (12.05.2026)","si_t2":"160 Aktien (11.05.2026)","si_t3":"20 Aktien (08.05.2026)","rsi14":69.17143075704239,"ma50":6.466999979019165,"ma200":7.717550020217896,"inst_ownership":null,"sec_13f_note":null,"52w_high":14.64,"52w_low":4.07,"avg_vol_20d":172060.45,"cur_vol":74109.0,"cur_open":8.949999809265137,"prev_close":8.90999984741211,"market_cap":198397712,"earnings_days":null,"earnings_date_str":null,"pc_ratio":null,"atm_iv":null,"options_expiry":null,"options_gamma_call_oi":null,"rel_strength_20d":30.995060283105147,"perf_20d":36.26706121865393,"cost_to_borrow":null,"utilization":null,"borrow_rate":null,"sparkline":null,"news":[{"title":"H\u00f6hepunkte der Telefonkonferenz zum 1. Quartal 2026 von Digimarc Corp (DMRC): Strategische Erfolge inmitten von Umsatzschwierigkeiten","link":"https://finance.yahoo.com/news/digimarc-corp-dmrc-q1-2026-050113954.html","time":"13.05.2026 05:01","source":"Yahoo Finance","ts":1778648473},{"title":"Highlights der Digimarc Q1 Earnings Call","link":"https://www.marketbeat.com/instant-alerts/digimarc-q1-earnings-call-highlights-2026-05-12/?utm_source=yahoofinance&utm_medium=yahoofinance","time":"12.05.2026 23:07","source":"Yahoo Finance","ts":1778627220},{"title":"Wir glauben, dass Digimarc (NASDAQ:DMRC) es sich leisten kann, das Gesch\u00e4ftswachstum voranzutreiben","link":"https://finance.yahoo.com/markets/stocks/articles/think-digimarc-nasdaq-dmrc-afford-121412125.html","time":"08.05.2026 12:14","source":"Yahoo Finance","ts":1778242452}],"card_html":"<div class=\"card-top\">\n    <div class=\"card-left\">\n      \n      <div class=\"ticker-block\">\n        <div class=\"ticker-row\">\n          <span class=\"ticker\">DMRC</span>\n          \n          <a class=\"sa-chart-btn\" href=\"https://stockanalysis.com/stocks/dmrc/\" target=\"_blank\" rel=\"noopener noreferrer\" title=\"Stockanalysis Chart &amp; Short-Interest\"><svg viewBox=\"0 0 24 24\" fill=\"none\" stroke=\"currentColor\" stroke-width=\"2.5\" stroke-linecap=\"round\" stroke-linejoin=\"round\" aria-hidden=\"true\"><path d=\"M15 3h6v6\"/><path d=\"M10 14 21 3\"/><path d=\"M21 14v5a2 2 0 0 1-2 2H5a2 2 0 0 1-2-2V5a2 2 0 0 1 2-2h5\"/></svg><span>Chart</span></a>\n          <span class=\"price-tag\">$8.98</span>\n          \n        </div>\n        <span class=\"company\">Digimarc Corporation</span>\n        <span class=\"sector-tag\">Technology \u00b7 Software - Application</span>\n      </div>\n    </div>\n    <div class=\"score-block sort-setup\"><div class=\"sb-row\" data-sb=\"conviction\"><span class=\"sb-num\" style=\"color:#94a3b8\">41</span><span class=\"sb-lbl\">Conviction</span><div class=\"sb-track\"><div class=\"sb-fill\" style=\"width:41%;background:#94a3b8\"></div></div><span class=\"sb-conv-action\" style=\"color:var(--txt-dim)\">Setup gut, aber Phase oder Marktkontext ung\u00fcnstig. Genau hinschauen.</span></div><div class=\"sb-row\" data-sb=\"setup\"><span class=\"sb-num\" style=\"color:#f97316\">48.6</span><span class=\"sb-lbl\">Setup-Score</span><div class=\"sb-track\"><div class=\"sb-fill\" style=\"width:49%;background:#f97316\"></div></div></div><div class=\"sb-row\" data-sb=\"monster\"><span class=\"sb-num\" style=\"color:#f97316\">49</span><span class=\"sb-lbl\">Monster-Score</span><div class=\"sb-track\"><div class=\"sb-fill\" style=\"width:49%;background:#f97316\"></div></div></div></div>\n  </div>\n  <div class=\"sub-scores-wrap\"><div class=\"sub-scores-header\">SETUP-ANALYSE</div><div class=\"sub-scores-hint\">unabh\u00e4ngige Qualit\u00e4tsindikatoren</div><div class=\"sub-scores\"><span class=\"sub-score\" title=\"Diese Werte sind unabh\u00e4ngige Qualit\u00e4tsindikatoren und ergeben nicht den Gesamt-Score\"><span class=\"sub-score-lbl\">Struktur</span><span class=\"sub-score-val\" style=\"color:#22c55e\">31/40</span><span class=\"sub-score-bar\"><span class=\"sub-score-fill\" style=\"width:78%;background:#22c55e\"></span></span></span><span class=\"sub-score\" title=\"Diese Werte sind unabh\u00e4ngige Qualit\u00e4tsindikatoren und ergeben nicht den Gesamt-Score\"><span class=\"sub-score-lbl\">Katalysator</span><span class=\"sub-score-val\" style=\"color:#94a3b8\">0/35</span><span class=\"sub-score-bar\"><span class=\"sub-score-fill\" style=\"width:0%;background:#94a3b8\"></span></span></span><span class=\"sub-score\" title=\"Diese Werte sind unabh\u00e4ngige Qualit\u00e4tsindikatoren und ergeben nicht den Gesamt-Score\"><span class=\"sub-score-lbl\">Timing</span><span class=\"sub-score-val\" style=\"color:#94a3b8\">4/35</span><span class=\"sub-score-bar\"><span class=\"sub-score-fill\" style=\"width:12%;background:#94a3b8\"></span></span></span></div></div>\n  <p class=\"spark-placeholder\">Verlauf ab morgen verf\u00fcgbar.</p>\n  <div class=\"metrics-row\">\n    <div class=\"metric-box\" style=\"--mc:#22c55e\">\n      <span class=\"m-val\">30.7%</span>\n      <span class=\"m-lbl\">Short Float</span>\n    </div>\n    <div class=\"metric-box\" style=\"--mc:#22c55e\">\n      <span class=\"m-val\">14.6d</span>\n      <span class=\"m-lbl\">Days to Cover</span>\n    </div>\n    <div class=\"metric-box\" style=\"--mc:#ef4444\">\n      <span class=\"m-val\">0.4\u00d7</span>\n      <span class=\"m-lbl\">Volumen</span>\n    </div>\n    <div class=\"metric-box\" style=\"--mc:#f59e0b\">\n      <span class=\"m-val\">+0.8%<br><span style=\"font-size:0.75em;color:var(--color-text-secondary)\">5T: +9.8%</span></span>\n      <span class=\"m-lbl\">Momentum</span>\n    </div>\n    <div class=\"metric-box\" style=\"--mc:#22c55e\">\n      <span class=\"m-val\">13,9 Mio,</span>\n      <span class=\"m-lbl\">Float</span>\n    </div>\n    <div class=\"metric-box\" style=\"--mc:#f59e0b\">\n      <span class=\"m-val\">\u2192 stabil</span>\n      <span class=\"m-lbl\">SI-Trend</span>\n    </div>\n  </div>\n  <button class=\"details-btn\" onclick=\"wlToggleDetails(this)\" aria-expanded=\"false\">\n    <span class=\"details-arrow\">\u25bc</span><span> Details anzeigen</span>\n  </button>\n  <div class=\"details-body\">\n    <div class=\"detail-table-wrap\">\n      <table class=\"detail-table\">\n        \n        <tr><td>Conviction-Score</td><td><span style=\"font-weight:700\">41</span> <span style=\"color:var(--txt-dim);font-size:.85em\">(Setup 16/33 \u00b7 Earliness 0/28 \u00b7 Anomaly 14/28 \u00b7 Regime 11/11)</span><br><span style=\"color:var(--txt-dim);font-size:.85em\">Setup gut, aber Phase oder Marktkontext ung\u00fcnstig. Genau hinschauen.</span></td></tr>\n        <tr class=\"detail-group-header\"><td colspan=\"2\">Stammdaten</td></tr>\n        <tr><td>Marktkapitalisierung</td><td>$198 M</td></tr>\n        <tr><td>Float (frei handelbar)</td><td>13.9 Mio. Aktien</td></tr>\n        <tr><td>Sektor</td><td>Technology \u00b7 Software - Application</td></tr>\n        <tr><td>52W-Hoch / -Tief</td><td>$14.64 / $4.07</td></tr>\n        \n        <tr class=\"detail-group-header\"><td colspan=\"2\">Short-Daten</td></tr>\n        <tr><td>SEC-Meldungen</td><td><a href=\"https://www.sec.gov/cgi-bin/browse-edgar?action=getcompany&amp;CIK=DMRC&amp;type=&amp;dateb=&amp;owner=include&amp;count=10&amp;search_text=\" target=\"_blank\" rel=\"noopener noreferrer\" class=\"edgar-link\">EDGAR \u00f6ffnen \u2192</a></td></tr>\n        <tr><td>SI-Trend (3M)</td><td><span style=\"color:#f59e0b\">\u2192 Seitw\u00e4rts +4.8 %</span></td></tr>\n        <tr><td>SI Velocity (t\u00e4gl. \u00d8)</td><td><span style=\"color:#ef4444\">-204 Aktien/Tag</span></td></tr>\n        <tr><td>Short-Vol. T-1 (FINRA)</td><td>71 Aktien (12.05.2026)</td></tr>\n        <tr><td>Short-Vol. T-2</td><td>160 Aktien (11.05.2026)</td></tr>\n        <tr><td>Short-Vol. T-3</td><td>20 Aktien (08.05.2026)</td></tr>\n        <tr><td>Cost-to-Borrow</td><td>\u2014</td></tr><tr><td>Utilization</td><td>\u2014</td></tr>\n        <tr class=\"detail-group-header\"><td colspan=\"2\">Volumen &amp; Momentum</td></tr>\n        <tr><td>\u00d8 Volumen 20T</td><td>172,060</td></tr>\n        <tr><td>Heutiges Volumen</td><td>74,109</td></tr>\n        <tr><td>Float Turnover</td><td><span style=\"color:var(--txt-dim)\">0.01\u00d7 <span style=\"color:var(--txt-dim);font-size:.85em\">(0 Pkt)</span></span></td></tr>\n        <tr><td>Gap &amp; Hold</td><td><span style=\"color:var(--txt-dim)\">+0.4% Open \u00b7 kein Gap <span style=\"color:var(--txt-dim);font-size:.85em\">(0 Pkt)</span></span></td></tr>\n        <tr><td>RSI (14T)</td><td><span style=\"color:var(--txt)\">69.2</span></td></tr><tr><td>MA 50T / 200T</td><td>$6.47 / $7.72</td></tr><tr><td>Kurs vs. MA50</td><td><span style=\"color:#22c55e\">(+38.9%)</span></td></tr><tr><td>Rel. St\u00e4rke (20T)</td><td><span style=\"color:#22c55e\">+31.0% vs. S&amp;P 500 (Aktie +36.3%)</span></td></tr><tr><td>RS vs. SPY (20T)</td><td><span style=\"color:#22c55e\">+31.0% <span style=\"color:var(--txt-dim);font-size:.85em\">(+3 Pkt)</span></span></td></tr>\n        <tr class=\"detail-group-header\"><td colspan=\"2\">Katalysatoren</td></tr>\n        <tr><td>Letztes Earnings</td><td><span style=\"color:#22c55e\">\u2705 Beat +433%</span></td></tr>\n        <tr><td>Risiko-Detail</td><td style=\"color:#ef4444\">Hohes Short-Interesse (30.7 %) erh\u00f6ht die Volatilit\u00e4t deutlich. Micro-Cap ($198 M) \u2013 geringe Liquidit\u00e4t, Kursmanipulation m\u00f6glich.</td></tr>\n      </table>\n    </div>\n    \n    <div class=\"drivers-block\"><div class=\"drivers-header\"><span class=\"risk-badge\" style=\"color:#ef4444;border-color:#ef444455;background:#ef444422\">Risiko: HOCH</span></div><p class=\"drivers-synthesis\"><strong class=\"syn-pos\">Stark:</strong> Days-to-Cover 14.6d, Short Float 30.7%.</p><div class=\"drivers-cats\"><div class=\"drivers-cat drivers-strengths\"><div class=\"drivers-cat-hdr\">\u2713 St\u00e4rken</div><ul class=\"drivers-list\"><li><span class=\"drv-w drv-w-pos\">+23</span><span class=\"drv-lbl\">Days-to-Cover 14.6d</span></li><li><span class=\"drv-w drv-w-pos\">+20</span><span class=\"drv-lbl\">Short Float 30.7%</span></li><li><span class=\"drv-w drv-w-pos\">+8</span><span class=\"drv-lbl\">Float klein (13.9 M)</span></li><li><span class=\"drv-w drv-w-pos\">+3</span><span class=\"drv-lbl\">RS vs. SPY +31.0%</span></li></ul></div></div></div>\n  </div>\n  <button class=\"news-btn\" onclick=\"wlToggleNews(this)\" aria-expanded=\"false\">\n    <span class=\"news-arrow\">\u25bc</span><span class=\"news-label\"> Aktuelle Meldungen</span>\n  </button>\n  <div class=\"news-panel\" hidden>\n    <div class=\"ki-signal-block\">\n      <div class=\"ki-signal-header\">&#9889; KI-Agent Signale</div>\n      <div class=\"ki-signal-body\"></div>\n    </div>\n    <div class=\"news-items\"><div class=\"ni\"><a href=\"https://finance.yahoo.com/news/digimarc-corp-dmrc-q1-2026-050113954.html\" target=\"_blank\" rel=\"noopener noreferrer\">H\u00f6hepunkte der Telefonkonferenz zum 1. Quartal 2026 von Digimarc Corp (DMRC): Strategische Erfolge inmitten von Umsatzschwierigkeiten</a> <span class=\"ni-src\">(Yahoo Finance)</span><span class=\"ni-meta\">13.05.2026 05:01</span></div><div class=\"ni\"><a href=\"https://www.marketbeat.com/instant-alerts/digimarc-q1-earnings-call-highlights-2026-05-12/?utm_source=yahoofinance&utm_medium=yahoofinance\" target=\"_blank\" rel=\"noopener noreferrer\">Highlights der Digimarc Q1 Earnings Call</a> <span class=\"ni-src\">(Yahoo Finance)</span><span class=\"ni-meta\">12.05.2026 23:07</span></div><div class=\"ni\"><a href=\"https://finance.yahoo.com/markets/stocks/articles/think-digimarc-nasdaq-dmrc-afford-121412125.html\" target=\"_blank\" rel=\"noopener noreferrer\">Wir glauben, dass Digimarc (NASDAQ:DMRC) es sich leisten kann, das Gesch\u00e4ftswachstum voranzutreiben</a> <span class=\"ni-src\">(Yahoo Finance)</span><span class=\"ni-meta\">08.05.2026 12:14</span></div></div>\n    <div class=\"news-summary-box\">\n      <span class=\"summary-label\">Zusammenfassung</span>\n      <p class=\"summary-text\">Digimarc Corp (DMRC) sichert sich trotz Umsatzr\u00fcckg\u00e4ngen und Verz\u00f6gerungen bei der Einf\u00fchrung wichtige kommerzielle Auftr\u00e4ge und Upsells.</p>\n    </div>\n  </div>\n  <button class=\"ki-analyse-btn\" onclick=\"wlOpenKiAnalyse('DMRC', this)\">\n    KI-Analyse\n  </button>\n  <div class=\"ki-analyse-result\"></div>"},"SABR":{"score":21.12,"monster_score":null,"ki_signal_score":null,"ki_signal_confidence":null,"ki_signal_drivers":null,"company_name":"Sabre Corporation","sector":"Technology","flag":"\ud83c\uddfa\ud83c\uddf8","price":1.7450000047683716,"change":-4.64,"change_5d":-4.64,"change_2d":-8.64,"change_3d":-15.29,"spx_daily_perf":-0.10484809627340624,"short_float":17.27,"short_float_source":"yfinance","short_ratio":12.05,"rel_volume":0.13621508518836606,"rel_volume_yesterday":0.829,"float_shares":280541970,"si_trend":"down","si_trend_source":"finra","si_tpct":-29.8,"si_velocity":70.0,"si_accel":false,"si_t1":"1,245 Aktien (12.05.2026)","si_t2":"2,501 Aktien (11.05.2026)","si_t3":"5,530 Aktien (08.05.2026)","rsi14":48.07912191041078,"ma50":1.6727000045776368,"ma200":1.6701700004935265,"inst_ownership":null,"sec_13f_note":null,"52w_high":3.52,"52w_low":0.81,"avg_vol_20d":4804144.85,"cur_vol":654397.0,"cur_open":1.809999942779541,"prev_close":1.8300000429153442,"market_cap":689821696,"earnings_days":null,"earnings_date_str":"","pc_ratio":null,"atm_iv":null,"options_expiry":null,"options_gamma_call_oi":null,"rel_strength_20d":-6.124272854649023,"perf_20d":-0.8522719191002408,"cost_to_borrow":null,"utilization":null,"borrow_rate":null,"sparkline":null,"news":[],"card_html":"<div class=\"card-top\">\n    <div class=\"card-left\">\n      \n      <div class=\"ticker-block\">\n        <div class=\"ticker-row\">\n          <span class=\"ticker\">SABR</span>\n          \n          <a class=\"sa-chart-btn\" href=\"https://stockanalysis.com/stocks/sabr/\" target=\"_blank\" rel=\"noopener noreferrer\" title=\"Stockanalysis Chart &amp; Short-Interest\"><svg viewBox=\"0 0 24 24\" fill=\"none\" stroke=\"currentColor\" stroke-width=\"2.5\" stroke-linecap=\"round\" stroke-linejoin=\"round\" aria-hidden=\"true\"><path d=\"M15 3h6v6\"/><path d=\"M10 14 21 3\"/><path d=\"M21 14v5a2 2 0 0 1-2 2H5a2 2 0 0 1-2-2V5a2 2 0 0 1 2-2h5\"/></svg><span>Chart</span></a>\n          <span class=\"price-tag\">$1.75</span>\n          \n        </div>\n        <span class=\"company\">Sabre Corporation</span>\n        <span class=\"sector-tag\">Technology \u00b7 Software - Infrastructure</span>\n      </div>\n    </div>\n    <div class=\"score-block sort-setup\"><div class=\"sb-row\" data-sb=\"setup\"><span class=\"sb-num\" style=\"color:#ef4444\">21.1</span><span class=\"sb-lbl\">Setup-Score</span><div class=\"sb-track\"><div class=\"sb-fill\" style=\"width:21%;background:#ef4444\"></div></div></div><span class=\"score-below-min\" style=\"max-width:180px;color:#f59e0b;font-style:normal\">Schwaches Setup \u2014 Backtesting zeigt keine positive Rendite unter Score 40</span></div>\n  </div>\n  <div class=\"sub-scores-wrap\"><div class=\"sub-scores-header\">SETUP-ANALYSE</div><div class=\"sub-scores-hint\">unabh\u00e4ngige Qualit\u00e4tsindikatoren</div><div class=\"sub-scores\"><span class=\"sub-score\" title=\"Diese Werte sind unabh\u00e4ngige Qualit\u00e4tsindikatoren und ergeben nicht den Gesamt-Score\"><span class=\"sub-score-lbl\">Struktur</span><span class=\"sub-score-val\" style=\"color:#f59e0b\">20/40</span><span class=\"sub-score-bar\"><span class=\"sub-score-fill\" style=\"width:50%;background:#f59e0b\"></span></span></span><span class=\"sub-score\" title=\"Diese Werte sind unabh\u00e4ngige Qualit\u00e4tsindikatoren und ergeben nicht den Gesamt-Score\"><span class=\"sub-score-lbl\">Katalysator</span><span class=\"sub-score-val\" style=\"color:#94a3b8\">0/35</span><span class=\"sub-score-bar\"><span class=\"sub-score-fill\" style=\"width:0%;background:#94a3b8\"></span></span></span><span class=\"sub-score\" title=\"Diese Werte sind unabh\u00e4ngige Qualit\u00e4tsindikatoren und ergeben nicht den Gesamt-Score\"><span class=\"sub-score-lbl\">Timing</span><span class=\"sub-score-val\" style=\"color:#94a3b8\">0/35</span><span class=\"sub-score-bar\"><span class=\"sub-score-fill\" style=\"width:0%;background:#94a3b8\"></span></span></span></div></div>\n  <p class=\"spark-placeholder\">Verlauf ab morgen verf\u00fcgbar.</p>\n  <div class=\"metrics-row\">\n    <div class=\"metric-box\" style=\"--mc:#f59e0b\">\n      <span class=\"m-val\">17.3%</span>\n      <span class=\"m-lbl\">Short Float</span>\n    </div>\n    <div class=\"metric-box\" style=\"--mc:#22c55e\">\n      <span class=\"m-val\">12.1d</span>\n      <span class=\"m-lbl\">Days to Cover</span>\n    </div>\n    <div class=\"metric-box\" style=\"--mc:#ef4444\">\n      <span class=\"m-val\">0.1\u00d7</span>\n      <span class=\"m-lbl\">Volumen</span>\n    </div>\n    <div class=\"metric-box\" style=\"--mc:#f59e0b\">\n      <span class=\"m-val\">-4.6%<br><span style=\"font-size:0.75em;color:var(--color-text-secondary)\">5T: -4.6%</span></span>\n      <span class=\"m-lbl\">Momentum</span>\n    </div>\n    <div class=\"metric-box\" style=\"--mc:#ef4444\">\n      <span class=\"m-val\">280,5 Mio,</span>\n      <span class=\"m-lbl\">Float</span>\n    </div>\n    <div class=\"metric-box\" style=\"--mc:#ef4444\">\n      <span class=\"m-val\">\u2193 \u221230 %</span>\n      <span class=\"m-lbl\">SI-Trend</span>\n    </div>\n  </div>\n  <button class=\"details-btn\" onclick=\"wlToggleDetails(this)\" aria-expanded=\"false\">\n    <span class=\"details-arrow\">\u25bc</span><span> Details anzeigen</span>\n  </button>\n  <div class=\"details-body\">\n    <div class=\"detail-table-wrap\">\n      <table class=\"detail-table\">\n        \n        <tr><td>Conviction-Score</td><td><span style=\"color:var(--txt-dim)\">\u2014</span></td></tr>\n        <tr class=\"detail-group-header\"><td colspan=\"2\">Stammdaten</td></tr>\n        <tr><td>Marktkapitalisierung</td><td>$690 M</td></tr>\n        <tr><td>Float (frei handelbar)</td><td>280.5 Mio. Aktien</td></tr>\n        <tr><td>Sektor</td><td>Technology \u00b7 Software - Infrastructure</td></tr>\n        <tr><td>52W-Hoch / -Tief</td><td>$3.52 / $0.81</td></tr>\n        \n        <tr class=\"detail-group-header\"><td colspan=\"2\">Short-Daten</td></tr>\n        <tr><td>SEC-Meldungen</td><td><a href=\"https://www.sec.gov/cgi-bin/browse-edgar?action=getcompany&amp;CIK=SABR&amp;type=&amp;dateb=&amp;owner=include&amp;count=10&amp;search_text=\" target=\"_blank\" rel=\"noopener noreferrer\" class=\"edgar-link\">EDGAR \u00f6ffnen \u2192</a></td></tr>\n        <tr><td>SI-Trend (3M)</td><td><span style=\"color:#ef4444\">\u2193 Fallend \u221229.8 %</span></td></tr>\n        <tr><td>SI Velocity (t\u00e4gl. \u00d8)</td><td><span style=\"color:#22c55e\">+70 Aktien/Tag</span></td></tr>\n        <tr><td>Short-Vol. T-1 (FINRA)</td><td>1,245 Aktien (12.05.2026)</td></tr>\n        <tr><td>Short-Vol. T-2</td><td>2,501 Aktien (11.05.2026)</td></tr>\n        <tr><td>Short-Vol. T-3</td><td>5,530 Aktien (08.05.2026)</td></tr>\n        <tr><td>Cost-to-Borrow</td><td>\u2014</td></tr><tr><td>Utilization</td><td>\u2014</td></tr>\n        <tr class=\"detail-group-header\"><td colspan=\"2\">Volumen &amp; Momentum</td></tr>\n        <tr><td>\u00d8 Volumen 20T</td><td>4,804,145</td></tr>\n        <tr><td>Heutiges Volumen</td><td>654,397</td></tr>\n        <tr><td>Float Turnover</td><td><span style=\"color:var(--txt-dim)\">0.00\u00d7 <span style=\"color:var(--txt-dim);font-size:.85em\">(0 Pkt)</span></span></td></tr>\n        <tr><td>Gap &amp; Hold</td><td><span style=\"color:var(--txt-dim)\">-1.1% Open \u00b7 kein Gap <span style=\"color:var(--txt-dim);font-size:.85em\">(0 Pkt)</span></span></td></tr>\n        <tr><td>RSI (14T)</td><td><span style=\"color:var(--txt)\">48.1</span></td></tr><tr><td>MA 50T / 200T</td><td>$1.67 / $1.67</td></tr><tr><td>Kurs vs. MA50</td><td><span style=\"color:#22c55e\">(+4.3%)</span></td></tr><tr><td>Rel. St\u00e4rke (20T)</td><td><span style=\"color:#ef4444\">-6.1% vs. S&amp;P 500 (Aktie -0.9%)</span></td></tr><tr><td>RS vs. SPY (20T)</td><td><span style=\"color:#ef4444\">-6.1% <span style=\"color:var(--txt-dim);font-size:.85em\">(-3 Pkt)</span></span></td></tr>\n        <tr class=\"detail-group-header\"><td colspan=\"2\">Katalysatoren</td></tr>\n        \n        <tr><td>Risiko-Detail</td><td style=\"color:#f59e0b\">Small-Cap ($690 M) mit eingeschr\u00e4nkter Liquidit\u00e4t.</td></tr>\n      </table>\n    </div>\n    \n    <div class=\"drivers-block\"><div class=\"drivers-header\"><span class=\"risk-badge\" style=\"color:#f59e0b;border-color:#f59e0b55;background:#f59e0b22\">Risiko: MITTEL</span></div><p class=\"drivers-synthesis\"><strong class=\"syn-pos\">Stark:</strong> Days-to-Cover 12.1d, Short Float 17.3%. <strong class=\"syn-neg\">Schwach:</strong> Tagesverlust -4.6%, SI-Trend \u2193 \u221230%.</p><div class=\"drivers-cats\"><div class=\"drivers-cat drivers-strengths\"><div class=\"drivers-cat-hdr\">\u2713 St\u00e4rken</div><ul class=\"drivers-list\"><li><span class=\"drv-w drv-w-pos\">+23</span><span class=\"drv-lbl\">Days-to-Cover 12.1d</span></li><li><span class=\"drv-w drv-w-pos\">+11</span><span class=\"drv-lbl\">Short Float 17.3%</span></li></ul></div><div class=\"drivers-cat drivers-risks\"><div class=\"drivers-cat-hdr\">\u26a0 Risiken</div><ul class=\"drivers-list\"><li><span class=\"drv-w drv-w-neg\">\u22127</span><span class=\"drv-lbl\">Tagesverlust -4.6%</span></li><li><span class=\"drv-w drv-w-neg\">\u22125</span><span class=\"drv-lbl\">SI-Trend \u2193 \u221230%</span></li><li><span class=\"drv-w drv-w-neg\">\u22123</span><span class=\"drv-lbl\">RS vs. SPY -6.1%</span></li></ul></div></div></div>\n  </div>\n  <button class=\"news-btn\" onclick=\"wlToggleNews(this)\" aria-expanded=\"false\">\n    <span class=\"news-arrow\">\u25bc</span><span class=\"news-label\"> Aktuelle Meldungen</span>\n  </button>\n  <div class=\"news-panel\" hidden>\n    <div class=\"ki-signal-block\">\n      <div class=\"ki-signal-header\">&#9889; KI-Agent Signale</div>\n      <div class=\"ki-signal-body\"></div>\n    </div>\n    <div class=\"news-items\"><p class=\"no-news\">Keine Nachrichten verf\u00fcgbar.</p></div>\n    <div class=\"news-summary-box\">\n      <span class=\"summary-label\">Zusammenfassung</span>\n      <p class=\"summary-text\">Keine aktuellen Nachrichten verf\u00fcgbar.</p>\n    </div>\n  </div>\n  <button class=\"ki-analyse-btn\" onclick=\"wlOpenKiAnalyse('SABR', this)\">\n    KI-Analyse\n  </button>\n  <div class=\"ki-analyse-result\"></div>"},"IONQ":{"score":11.86,"monster_score":null,"ki_signal_score":null,"ki_signal_confidence":null,"ki_signal_drivers":null,"company_name":"IonQ, Inc.","sector":"Technology","flag":"\ud83c\uddfa\ud83c\uddf8","price":53.75,"change":-3.79,"change_5d":2.24,"change_2d":-5.52,"change_3d":9.16,"spx_daily_perf":-0.10484809627340624,"short_float":23.18,"short_float_source":"yfinance","short_ratio":3.61,"rel_volume":0.19288139256211723,"rel_volume_yesterday":1.239,"float_shares":370548810,"si_trend":"up","si_trend_source":"yfinance","si_tpct":5.7,"si_velocity":-29882.0,"si_accel":false,"si_t1":"129,602 Aktien (08.05.2026)","si_t2":"189,365 Aktien (07.05.2026)","si_t3":"\u2014","rsi14":64.33179565475103,"ma50":38.22740005493164,"ma200":46.824999990463255,"inst_ownership":null,"sec_13f_note":null,"52w_high":84.64,"52w_low":25.89,"avg_vol_20d":36294314.9,"cur_vol":7000498.0,"cur_open":55.939998626708984,"prev_close":55.869998931884766,"market_cap":20048328704,"earnings_days":null,"earnings_date_str":"","pc_ratio":null,"atm_iv":null,"options_expiry":null,"options_gamma_call_oi":null,"rel_strength_20d":19.00545571185006,"perf_20d":24.277456647398843,"cost_to_borrow":null,"utilization":null,"borrow_rate":null,"sparkline":null,"news":[],"card_html":"<div class=\"card-top\">\n    <div class=\"card-left\">\n      \n      <div class=\"ticker-block\">\n        <div class=\"ticker-row\">\n          <span class=\"ticker\">IONQ</span>\n          \n          <a class=\"sa-chart-btn\" href=\"https://stockanalysis.com/stocks/ionq/\" target=\"_blank\" rel=\"noopener noreferrer\" title=\"Stockanalysis Chart &amp; Short-Interest\"><svg viewBox=\"0 0 24 24\" fill=\"none\" stroke=\"currentColor\" stroke-width=\"2.5\" stroke-linecap=\"round\" stroke-linejoin=\"round\" aria-hidden=\"true\"><path d=\"M15 3h6v6\"/><path d=\"M10 14 21 3\"/><path d=\"M21 14v5a2 2 0 0 1-2 2H5a2 2 0 0 1-2-2V5a2 2 0 0 1 2-2h5\"/></svg><span>Chart</span></a>\n          <span class=\"price-tag\">$53.75</span>\n          \n        </div>\n        <span class=\"company\">IonQ, Inc.</span>\n        <span class=\"sector-tag\">Technology \u00b7 Computer Hardware</span><span class=\"squeeze-hist-badge\" title=\"Kursanstieg \u2265 50% in 5 Tagen bei Volumen \u2265 3\u00d7 vor 17 Tagen\">\u26a0\ufe0f Squeeze vor 17 Tagen</span>\n      </div>\n    </div>\n    <div class=\"score-block sort-setup\"><div class=\"sb-row\" data-sb=\"setup\"><span class=\"sb-num\" style=\"color:#ef4444\">11.9</span><span class=\"sb-lbl\">Setup-Score</span><div class=\"sb-track\"><div class=\"sb-fill\" style=\"width:12%;background:#ef4444\"></div></div></div><span class=\"score-below-min\" style=\"max-width:150px;font-style:normal\">Score zu niedrig f\u00fcr Squeeze-Signal</span></div>\n  </div>\n  <div class=\"sub-scores-wrap\"><div class=\"sub-scores-header\">SETUP-ANALYSE</div><div class=\"sub-scores-hint\">unabh\u00e4ngige Qualit\u00e4tsindikatoren</div><div class=\"sub-scores\"><span class=\"sub-score\" title=\"Diese Werte sind unabh\u00e4ngige Qualit\u00e4tsindikatoren und ergeben nicht den Gesamt-Score\"><span class=\"sub-score-lbl\">Struktur</span><span class=\"sub-score-val\" style=\"color:#94a3b8\">17/40</span><span class=\"sub-score-bar\"><span class=\"sub-score-fill\" style=\"width:42%;background:#94a3b8\"></span></span></span><span class=\"sub-score\" title=\"Diese Werte sind unabh\u00e4ngige Qualit\u00e4tsindikatoren und ergeben nicht den Gesamt-Score\"><span class=\"sub-score-lbl\">Katalysator</span><span class=\"sub-score-val\" style=\"color:#94a3b8\">0/35</span><span class=\"sub-score-bar\"><span class=\"sub-score-fill\" style=\"width:0%;background:#94a3b8\"></span></span></span><span class=\"sub-score\" title=\"Diese Werte sind unabh\u00e4ngige Qualit\u00e4tsindikatoren und ergeben nicht den Gesamt-Score\"><span class=\"sub-score-lbl\">Timing</span><span class=\"sub-score-val\" style=\"color:#94a3b8\">3/35</span><span class=\"sub-score-bar\"><span class=\"sub-score-fill\" style=\"width:9%;background:#94a3b8\"></span></span></span></div></div>\n  <p class=\"spark-placeholder\">Verlauf ab morgen verf\u00fcgbar.</p>\n  <div class=\"metrics-row\">\n    <div class=\"metric-box\" style=\"--mc:#f59e0b\">\n      <span class=\"m-val\">23.2%</span>\n      <span class=\"m-lbl\">Short Float</span>\n    </div>\n    <div class=\"metric-box\" style=\"--mc:#f59e0b\">\n      <span class=\"m-val\">3.6d</span>\n      <span class=\"m-lbl\">Days to Cover</span>\n    </div>\n    <div class=\"metric-box\" style=\"--mc:#ef4444\">\n      <span class=\"m-val\">0.2\u00d7</span>\n      <span class=\"m-lbl\">Volumen</span>\n    </div>\n    <div class=\"metric-box\" style=\"--mc:#f59e0b\">\n      <span class=\"m-val\">-3.8%<br><span style=\"font-size:0.75em;color:var(--color-text-secondary)\">5T: +2.2%</span></span>\n      <span class=\"m-lbl\">Momentum</span>\n    </div>\n    <div class=\"metric-box\" style=\"--mc:#ef4444\">\n      <span class=\"m-val\">370,5 Mio,</span>\n      <span class=\"m-lbl\">Float</span>\n    </div>\n    <div class=\"metric-box\" style=\"--mc:#22c55e\">\n      <span class=\"m-val\">\u2191 +6 %</span>\n      <span class=\"m-lbl\">SI-Trend</span>\n    </div>\n  </div>\n  <button class=\"details-btn\" onclick=\"wlToggleDetails(this)\" aria-expanded=\"false\">\n    <span class=\"details-arrow\">\u25bc</span><span> Details anzeigen</span>\n  </button>\n  <div class=\"details-body\">\n    <div class=\"detail-table-wrap\">\n      <table class=\"detail-table\">\n        \n        <tr><td>Conviction-Score</td><td><span style=\"color:var(--txt-dim)\">\u2014</span></td></tr>\n        <tr class=\"detail-group-header\"><td colspan=\"2\">Stammdaten</td></tr>\n        <tr><td>Marktkapitalisierung</td><td>$20.0 B</td></tr>\n        <tr><td>Float (frei handelbar)</td><td>370.5 Mio. Aktien</td></tr>\n        <tr><td>Sektor</td><td>Technology \u00b7 Computer Hardware</td></tr>\n        <tr><td>52W-Hoch / -Tief</td><td>$84.64 / $25.89</td></tr>\n        \n        <tr class=\"detail-group-header\"><td colspan=\"2\">Short-Daten</td></tr>\n        <tr><td>SEC-Meldungen</td><td><a href=\"https://www.sec.gov/cgi-bin/browse-edgar?action=getcompany&amp;CIK=IONQ&amp;type=&amp;dateb=&amp;owner=include&amp;count=10&amp;search_text=\" target=\"_blank\" rel=\"noopener noreferrer\" class=\"edgar-link\">EDGAR \u00f6ffnen \u2192</a></td></tr>\n        <tr><td>SI-Trend (3M)</td><td><span style=\"color:#22c55e\">\u2191 Steigend +5.7 %</span></td></tr>\n        <tr><td>SI Velocity (t\u00e4gl. \u00d8)</td><td><span style=\"color:#ef4444\">-29.882 Aktien/Tag</span></td></tr>\n        <tr><td>Short-Vol. T-1 (FINRA)</td><td>129,602 Aktien (08.05.2026)</td></tr>\n        <tr><td>Short-Vol. T-2</td><td>189,365 Aktien (07.05.2026)</td></tr>\n        <tr><td>Short-Vol. T-3</td><td>\u2014</td></tr>\n        <tr><td>Cost-to-Borrow</td><td>\u2014</td></tr><tr><td>Utilization</td><td>\u2014</td></tr>\n        <tr class=\"detail-group-header\"><td colspan=\"2\">Volumen &amp; Momentum</td></tr>\n        <tr><td>\u00d8 Volumen 20T</td><td>36,294,315</td></tr>\n        <tr><td>Heutiges Volumen</td><td>7,000,498</td></tr>\n        <tr><td>Float Turnover</td><td><span style=\"color:var(--txt-dim)\">0.02\u00d7 <span style=\"color:var(--txt-dim);font-size:.85em\">(0 Pkt)</span></span></td></tr>\n        <tr><td>Gap &amp; Hold</td><td><span style=\"color:var(--txt-dim)\">+0.1% Open \u00b7 kein Gap <span style=\"color:var(--txt-dim);font-size:.85em\">(0 Pkt)</span></span></td></tr>\n        <tr><td>RSI (14T)</td><td><span style=\"color:var(--txt)\">64.3</span></td></tr><tr><td>MA 50T / 200T</td><td>$38.23 / $46.82</td></tr><tr><td>Kurs vs. MA50</td><td><span style=\"color:#22c55e\">(+40.6%)</span></td></tr><tr><td>Rel. St\u00e4rke (20T)</td><td><span style=\"color:#22c55e\">+19.0% vs. S&amp;P 500 (Aktie +24.3%)</span></td></tr><tr><td>RS vs. SPY (20T)</td><td><span style=\"color:#22c55e\">+19.0% <span style=\"color:var(--txt-dim);font-size:.85em\">(+3 Pkt)</span></span></td></tr>\n        <tr class=\"detail-group-header\"><td colspan=\"2\">Katalysatoren</td></tr>\n        \n        <tr><td>Risiko-Detail</td><td style=\"color:#22c55e\">Moderates Risikoprofil f\u00fcr einen Squeeze-Kandidaten.</td></tr>\n      </table>\n    </div>\n    \n    <div class=\"drivers-block\"><div class=\"drivers-header\"><span class=\"risk-badge\" style=\"color:#22c55e;border-color:#22c55e55;background:#22c55e22\">Risiko: NIEDRIG</span></div><p class=\"drivers-synthesis\"><strong class=\"syn-pos\">Stark:</strong> Short Float 23.2%, SI-Trend \u2191 +6%. <strong class=\"syn-neg\">Schwach:</strong> Tagesverlust -3.8%.</p><div class=\"drivers-cats\"><div class=\"drivers-cat drivers-strengths\"><div class=\"drivers-cat-hdr\">\u2713 St\u00e4rken</div><ul class=\"drivers-list\"><li><span class=\"drv-w drv-w-pos\">+15</span><span class=\"drv-lbl\">Short Float 23.2%</span></li><li><span class=\"drv-w drv-w-pos\">+5</span><span class=\"drv-lbl\">SI-Trend \u2191 +6%</span></li><li><span class=\"drv-w drv-w-pos\">+3</span><span class=\"drv-lbl\">RS vs. SPY +19.0%</span></li></ul></div><div class=\"drivers-cat drivers-risks\"><div class=\"drivers-cat-hdr\">\u26a0 Risiken</div><ul class=\"drivers-list\"><li><span class=\"drv-w drv-w-neg\">\u22126</span><span class=\"drv-lbl\">Tagesverlust -3.8%</span></li></ul></div></div></div>\n  </div>\n  <button class=\"news-btn\" onclick=\"wlToggleNews(this)\" aria-expanded=\"false\">\n    <span class=\"news-arrow\">\u25bc</span><span class=\"news-label\"> Aktuelle Meldungen</span>\n  </button>\n  <div class=\"news-panel\" hidden>\n    <div class=\"ki-signal-block\">\n      <div class=\"ki-signal-header\">&#9889; KI-Agent Signale</div>\n      <div class=\"ki-signal-body\"></div>\n    </div>\n    <div class=\"news-items\"><p class=\"no-news\">Keine Nachrichten verf\u00fcgbar.</p></div>\n    <div class=\"news-summary-box\">\n      <span class=\"summary-label\">Zusammenfassung</span>\n      <p class=\"summary-text\">Keine aktuellen Nachrichten verf\u00fcgbar.</p>\n    </div>\n  </div>\n  <button class=\"ki-analyse-btn\" onclick=\"wlOpenKiAnalyse('IONQ', this)\">\n    KI-Analyse\n  </button>\n  <div class=\"ki-analyse-result\"></div>"},"AMC":{"score":4.6,"monster_score":null,"ki_signal_score":null,"ki_signal_confidence":null,"ki_signal_drivers":null,"company_name":"AMC Entertainment Holdings, Inc.","sector":"Communication Services","flag":"\ud83c\uddfa\ud83c\uddf8","price":1.3450000286102295,"change":0.37,"change_5d":-17.99,"change_2d":-4.61,"change_3d":-10.33,"spx_daily_perf":-0.10484809627340624,"short_float":15.42,"short_float_source":"yfinance","short_ratio":3.0,"rel_volume":0.13008105231951078,"rel_volume_yesterday":0.63,"float_shares":551352138,"si_trend":"down","si_trend_source":"finra","si_tpct":-58.6,"si_velocity":-6774.0,"si_accel":true,"si_t1":"98,391 Aktien (12.05.2026)","si_t2":"29,887 Aktien (11.05.2026)","si_t3":"9,933 Aktien (08.05.2026)","rsi14":42.069175595160175,"ma50":1.3231000006198883,"ma200":2.028824996650219,"inst_ownership":null,"sec_13f_note":null,"52w_high":4.08,"52w_low":0.93,"avg_vol_20d":31147042.0,"cur_vol":4051640.0,"cur_open":1.3200000524520874,"prev_close":1.340000033378601,"market_cap":993945792,"earnings_days":null,"earnings_date_str":"","pc_ratio":null,"atm_iv":null,"options_expiry":null,"options_gamma_call_oi":null,"rel_strength_20d":-24.733074996998674,"perf_20d":-19.461074061449892,"cost_to_borrow":null,"utilization":null,"borrow_rate":null,"sparkline":null,"news":[],"card_html":"<div class=\"card-top\">\n    <div class=\"card-left\">\n      \n      <div class=\"ticker-block\">\n        <div class=\"ticker-row\">\n          <span class=\"ticker\">AMC</span>\n          \n          <a class=\"sa-chart-btn\" href=\"https://stockanalysis.com/stocks/amc/\" target=\"_blank\" rel=\"noopener noreferrer\" title=\"Stockanalysis Chart &amp; Short-Interest\"><svg viewBox=\"0 0 24 24\" fill=\"none\" stroke=\"currentColor\" stroke-width=\"2.5\" stroke-linecap=\"round\" stroke-linejoin=\"round\" aria-hidden=\"true\"><path d=\"M15 3h6v6\"/><path d=\"M10 14 21 3\"/><path d=\"M21 14v5a2 2 0 0 1-2 2H5a2 2 0 0 1-2-2V5a2 2 0 0 1 2-2h5\"/></svg><span>Chart</span></a>\n          <span class=\"price-tag\">$1.35</span>\n          \n        </div>\n        <span class=\"company\">AMC Entertainment Holdings, Inc.</span>\n        <span class=\"sector-tag\">Communication Services \u00b7 Entertainment</span>\n      </div>\n    </div>\n    <div class=\"score-block sort-setup\"><div class=\"sb-row\" data-sb=\"setup\"><span class=\"sb-num\" style=\"color:#ef4444\">4.6</span><span class=\"sb-lbl\">Setup-Score</span><div class=\"sb-track\"><div class=\"sb-fill\" style=\"width:5%;background:#ef4444\"></div></div></div><span class=\"score-below-min\" style=\"max-width:150px;font-style:normal\">Score zu niedrig f\u00fcr Squeeze-Signal</span></div>\n  </div>\n  <div class=\"sub-scores-wrap\"><div class=\"sub-scores-header\">SETUP-ANALYSE</div><div class=\"sub-scores-hint\">unabh\u00e4ngige Qualit\u00e4tsindikatoren</div><div class=\"sub-scores\"><span class=\"sub-score\" title=\"Diese Werte sind unabh\u00e4ngige Qualit\u00e4tsindikatoren und ergeben nicht den Gesamt-Score\"><span class=\"sub-score-lbl\">Struktur</span><span class=\"sub-score-val\" style=\"color:#94a3b8\">10/40</span><span class=\"sub-score-bar\"><span class=\"sub-score-fill\" style=\"width:25%;background:#94a3b8\"></span></span></span><span class=\"sub-score\" title=\"Diese Werte sind unabh\u00e4ngige Qualit\u00e4tsindikatoren und ergeben nicht den Gesamt-Score\"><span class=\"sub-score-lbl\">Katalysator</span><span class=\"sub-score-val\" style=\"color:#94a3b8\">0/35</span><span class=\"sub-score-bar\"><span class=\"sub-score-fill\" style=\"width:0%;background:#94a3b8\"></span></span></span><span class=\"sub-score\" title=\"Diese Werte sind unabh\u00e4ngige Qualit\u00e4tsindikatoren und ergeben nicht den Gesamt-Score\"><span class=\"sub-score-lbl\">Timing</span><span class=\"sub-score-val\" style=\"color:#94a3b8\">0/35</span><span class=\"sub-score-bar\"><span class=\"sub-score-fill\" style=\"width:0%;background:#94a3b8\"></span></span></span></div></div>\n  <p class=\"spark-placeholder\">Verlauf ab morgen verf\u00fcgbar.</p>\n  <div class=\"metrics-row\">\n    <div class=\"metric-box\" style=\"--mc:#f59e0b\">\n      <span class=\"m-val\">15.4%</span>\n      <span class=\"m-lbl\">Short Float</span>\n    </div>\n    <div class=\"metric-box\" style=\"--mc:#f59e0b\">\n      <span class=\"m-val\">3.0d</span>\n      <span class=\"m-lbl\">Days to Cover</span>\n    </div>\n    <div class=\"metric-box\" style=\"--mc:#ef4444\">\n      <span class=\"m-val\">0.1\u00d7</span>\n      <span class=\"m-lbl\">Volumen</span>\n    </div>\n    <div class=\"metric-box\" style=\"--mc:#f59e0b\">\n      <span class=\"m-val\">+0.4%<br><span style=\"font-size:0.75em;color:var(--color-text-secondary)\">5T: -18.0%</span></span>\n      <span class=\"m-lbl\">Momentum</span>\n    </div>\n    <div class=\"metric-box\" style=\"--mc:#ef4444\">\n      <span class=\"m-val\">551,4 Mio,</span>\n      <span class=\"m-lbl\">Float</span>\n    </div>\n    <div class=\"metric-box\" style=\"--mc:#ef4444\">\n      <span class=\"m-val\">\u2193 \u221259 %</span>\n      <span class=\"m-lbl\">SI-Trend</span>\n    </div>\n  </div>\n  <button class=\"details-btn\" onclick=\"wlToggleDetails(this)\" aria-expanded=\"false\">\n    <span class=\"details-arrow\">\u25bc</span><span> Details anzeigen</span>\n  </button>\n  <div class=\"details-body\">\n    <div class=\"detail-table-wrap\">\n      <table class=\"detail-table\">\n        \n        <tr><td>Conviction-Score</td><td><span style=\"color:var(--txt-dim)\">\u2014</span></td></tr>\n        <tr class=\"detail-group-header\"><td colspan=\"2\">Stammdaten</td></tr>\n        <tr><td>Marktkapitalisierung</td><td>$994 M</td></tr>\n        <tr><td>Float (frei handelbar)</td><td>551.4 Mio. Aktien</td></tr>\n        <tr><td>Sektor</td><td>Communication Services \u00b7 Entertainment</td></tr>\n        <tr><td>52W-Hoch / -Tief</td><td>$4.08 / $0.93</td></tr>\n        \n        <tr class=\"detail-group-header\"><td colspan=\"2\">Short-Daten</td></tr>\n        <tr><td>SEC-Meldungen</td><td><a href=\"https://www.sec.gov/cgi-bin/browse-edgar?action=getcompany&amp;CIK=AMC&amp;type=&amp;dateb=&amp;owner=include&amp;count=10&amp;search_text=\" target=\"_blank\" rel=\"noopener noreferrer\" class=\"edgar-link\">EDGAR \u00f6ffnen \u2192</a></td></tr>\n        <tr><td>SI-Trend (3M)</td><td><span style=\"color:#ef4444\">\u2193 Fallend \u221258.6 %</span></td></tr>\n        <tr><td>SI Velocity (t\u00e4gl. \u00d8)</td><td><span style=\"color:#ef4444\">-6.774 Aktien/Tag \u26a1 Beschleunigung</span></td></tr>\n        <tr><td>Short-Vol. T-1 (FINRA)</td><td>98,391 Aktien (12.05.2026)</td></tr>\n        <tr><td>Short-Vol. T-2</td><td>29,887 Aktien (11.05.2026)</td></tr>\n        <tr><td>Short-Vol. T-3</td><td>9,933 Aktien (08.05.2026)</td></tr>\n        <tr><td>Cost-to-Borrow</td><td>\u2014</td></tr><tr><td>Utilization</td><td>\u2014</td></tr>\n        <tr class=\"detail-group-header\"><td colspan=\"2\">Volumen &amp; Momentum</td></tr>\n        <tr><td>\u00d8 Volumen 20T</td><td>31,147,042</td></tr>\n        <tr><td>Heutiges Volumen</td><td>4,051,640</td></tr>\n        <tr><td>Float Turnover</td><td><span style=\"color:var(--txt-dim)\">0.01\u00d7 <span style=\"color:var(--txt-dim);font-size:.85em\">(0 Pkt)</span></span></td></tr>\n        <tr><td>Gap &amp; Hold</td><td><span style=\"color:var(--txt-dim)\">-1.5% Open \u00b7 kein Gap <span style=\"color:var(--txt-dim);font-size:.85em\">(0 Pkt)</span></span></td></tr>\n        <tr><td>RSI (14T)</td><td><span style=\"color:var(--txt)\">42.1</span></td></tr><tr><td>MA 50T / 200T</td><td>$1.32 / $2.03</td></tr><tr><td>Kurs vs. MA50</td><td><span style=\"color:#22c55e\">(+1.7%)</span></td></tr><tr><td>Rel. St\u00e4rke (20T)</td><td><span style=\"color:#ef4444\">-24.7% vs. S&amp;P 500 (Aktie -19.5%)</span></td></tr><tr><td>RS vs. SPY (20T)</td><td><span style=\"color:#ef4444\">-24.7% <span style=\"color:var(--txt-dim);font-size:.85em\">(-3 Pkt)</span></span></td></tr>\n        <tr class=\"detail-group-header\"><td colspan=\"2\">Katalysatoren</td></tr>\n        \n        <tr><td>Risiko-Detail</td><td style=\"color:#f59e0b\">Small-Cap ($994 M) mit eingeschr\u00e4nkter Liquidit\u00e4t.</td></tr>\n      </table>\n    </div>\n    \n    <div class=\"drivers-block\"><div class=\"drivers-header\"><span class=\"risk-badge\" style=\"color:#f59e0b;border-color:#f59e0b55;background:#f59e0b22\">Risiko: MITTEL</span></div><p class=\"drivers-synthesis\"><strong class=\"syn-pos\">Stark:</strong> Short Float 15.4%. <strong class=\"syn-neg\">Schwach:</strong> SI-Trend \u2193 \u221259%, RS vs. SPY -24.7%.</p><div class=\"drivers-cats\"><div class=\"drivers-cat drivers-strengths\"><div class=\"drivers-cat-hdr\">\u2713 St\u00e4rken</div><ul class=\"drivers-list\"><li><span class=\"drv-w drv-w-pos\">+10</span><span class=\"drv-lbl\">Short Float 15.4%</span></li></ul></div><div class=\"drivers-cat drivers-risks\"><div class=\"drivers-cat-hdr\">\u26a0 Risiken</div><ul class=\"drivers-list\"><li><span class=\"drv-w drv-w-neg\">\u22125</span><span class=\"drv-lbl\">SI-Trend \u2193 \u221259%</span></li><li><span class=\"drv-w drv-w-neg\">\u22123</span><span class=\"drv-lbl\">RS vs. SPY -24.7%</span></li></ul></div></div></div>\n  </div>\n  <button class=\"news-btn\" onclick=\"wlToggleNews(this)\" aria-expanded=\"false\">\n    <span class=\"news-arrow\">\u25bc</span><span class=\"news-label\"> Aktuelle Meldungen</span>\n  </button>\n  <div class=\"news-panel\" hidden>\n    <div class=\"ki-signal-block\">\n      <div class=\"ki-signal-header\">&#9889; KI-Agent Signale</div>\n      <div class=\"ki-signal-body\"></div>\n    </div>\n    <div class=\"news-items\"><p class=\"no-news\">Keine Nachrichten verf\u00fcgbar.</p></div>\n    <div class=\"news-summary-box\">\n      <span class=\"summary-label\">Zusammenfassung</span>\n      <p class=\"summary-text\">Keine aktuellen Nachrichten verf\u00fcgbar.</p>\n    </div>\n  </div>\n  <button class=\"ki-analyse-btn\" onclick=\"wlOpenKiAnalyse('AMC', this)\">\n    KI-Analyse\n  </button>\n  <div class=\"ki-analyse-result\"></div>"}},"monster_scores":{"SLS":68.6,"HUMA":55.4,"CCCC":55.0,"SNSE":52.1,"TTEC":51.8,"DDD":59.0,"RIGL":59.0,"CSIQ":48.8,"DMRC":48.6,"GO":46.4},"setup_scores":{"SLS":68.6,"HUMA":55.4,"CCCC":55.0,"SNSE":52.1,"TTEC":51.8,"DDD":49.3,"RIGL":48.8,"CSIQ":48.8,"DMRC":48.6,"GO":46.4},"gap_states":{"SLS":{"pct":20.98,"state":"weak_hold"},"HUMA":{"pct":-1.67,"state":"no_gap"},"CCCC":{"pct":0.0,"state":"no_gap"},"SNSE":{"pct":0.0,"state":"no_gap"},"TTEC":{"pct":0.41,"state":"no_gap"},"DDD":{"pct":3.54,"state":"weak_hold"},"RIGL":{"pct":2.15,"state":"no_gap"},"CSIQ":{"pct":2.47,"state":"no_gap"},"DMRC":{"pct":0.45,"state":"no_gap"},"GO":{"pct":-1.88,"state":"no_gap"}},"top10_metrics":{"SLS":{"rsi14":67.59519890730239,"ma21":5.043739776534199,"change_2d":14.38,"change_3d":19.86},"HUMA":{"rsi14":62.00749516047525,"ma21":0.8869853521083615,"change_2d":4.5,"change_3d":-1.42},"CCCC":{"rsi14":71.66117265867709,"ma21":2.996460324162831,"change_2d":15.93,"change_3d":24.58},"SNSE":{"rsi14":33.762443013478155,"ma21":26.233798065443935,"change_2d":5.55,"change_3d":-6.5},"TTEC":{"rsi14":43.62446556832919,"ma21":2.816823804674219,"change_2d":-0.39,"change_3d":-4.43},"DDD":{"rsi14":75.48908758633618,"ma21":2.4574582641435763,"change_2d":26.1,"change_3d":28.14},"RIGL":{"rsi14":62.78657118901287,"ma21":29.045800344870706,"change_2d":23.32,"change_3d":24.08},"CSIQ":{"rsi14":71.54501268710999,"ma21":16.64338034903107,"change_2d":2.46,"change_3d":1.38},"DMRC":{"rsi14":69.17143075704239,"ma21":7.8302362217156185,"change_2d":0.34,"change_3d":-4.06},"GO":{"rsi14":56.939549813203335,"ma21":7.824760283092253,"change_2d":3.5,"change_3d":-0.79}},"conviction_scores":{"SLS":{"score":48,"components":{"setup":23,"earliness":0,"anomaly":14,"regime":11},"action_text":"Setup gut, aber Phase oder Marktkontext ung\u00fcnstig. Genau hinschauen.","level":"low"},"HUMA":{"score":57,"components":{"setup":18,"earliness":0,"anomaly":28,"regime":11},"action_text":"Substrat stark, Timing-Signal fehlt. Auf Volume-Spike oder Anomalie-Trigger warten.","level":"medium"},"CCCC":{"score":43,"components":{"setup":18,"earliness":0,"anomaly":14,"regime":11},"action_text":"Setup gut, aber Phase oder Marktkontext ung\u00fcnstig. Genau hinschauen.","level":"low"},"SNSE":{"score":28,"components":{"setup":17,"earliness":0,"anomaly":0,"regime":11},"action_text":"Aktuell kein klares Aktions-Signal.","level":"low"},"TTEC":{"score":50,"components":{"setup":17,"earliness":8,"anomaly":14,"regime":11},"action_text":"Substrat stark, Timing-Signal fehlt. Auf Volume-Spike oder Anomalie-Trigger warten.","level":"medium"},"DDD":{"score":27,"components":{"setup":16,"earliness":0,"anomaly":0,"regime":11},"action_text":"Aktuell kein klares Aktions-Signal.","level":"low"},"RIGL":{"score":27,"components":{"setup":16,"earliness":0,"anomaly":0,"regime":11},"action_text":"Aktuell kein klares Aktions-Signal.","level":"low"},"CSIQ":{"score":55,"components":{"setup":16,"earliness":0,"anomaly":28,"regime":11},"action_text":"Substrat stark, Timing-Signal fehlt. Auf Volume-Spike oder Anomalie-Trigger warten.","level":"medium"},"DMRC":{"score":41,"components":{"setup":16,"earliness":0,"anomaly":14,"regime":11},"action_text":"Setup gut, aber Phase oder Marktkontext ung\u00fcnstig. Genau hinschauen.","level":"low"},"GO":{"score":40,"components":{"setup":15,"earliness":0,"anomaly":14,"regime":11},"action_text":"Setup gut, aber Phase oder Marktkontext ung\u00fcnstig. Genau hinschauen.","level":"low"}},"positions":{"AMC":{"entry_date":"2026-05-01","entry_price":1.5,"shares":500,"entry_fx":0.8549,"fx_estimated":true,"entry_dtc":null,"entry_short_float":null,"entry_cost_to_borrow":null,"entry_snapshot_ts":null,"exit_state":{"exit_pressure":71,"triggers":{"score_decay":{"score":0,"warn":false,"crit":false,"available":false,"reason":"score_history zu kurz"},"profit_lock":{"score":100,"warn":true,"crit":true,"details":{"pnl_pct":-0.1033,"peak_pnl_pct":0.16,"drawdown_from_peak":0.2633,"score_drop_from_peak":null}},"overheated":{"score":28,"warn":false,"crit":false,"details":{"rsi14":42.069175595160175,"move_2d_pct":-0.0461,"move_3d_pct":-0.1033,"move_3d_available":true}},"setup_erosion":{"score":0,"warn":false,"crit":false,"available":false,"reason":"no_entry_snapshot"},"catalyst":{"score":0,"warn":false,"crit":false,"available":false,"reason":"kein Earnings-Datum aus Finnhub/yfinance"},"trend_break":{"score":100,"warn":true,"crit":true,"details":{"ma21":1.4802,"price":1.345,"drop_pct":9.14}}},"peak_score_since_entry":null,"peak_pnl_pct_since_entry":0.16,"current_score":null,"current_pnl_pct":-0.1033,"prev_exit_pressure":71,"computed_at":"2026-05-13T14:11:06Z"}},"SABR":{"entry_date":"2026-05-07","entry_price":1.95,"shares":50,"entry_fx":0.8516,"fx_estimated":false,"entry_dtc":null,"entry_short_float":null,"entry_cost_to_borrow":null,"entry_snapshot_ts":null,"exit_state":{"exit_pressure":54,"triggers":{"score_decay":{"score":0,"warn":false,"crit":false,"available":false,"reason":"score_history zu kurz"},"profit_lock":{"score":74,"warn":true,"crit":false,"details":{"pnl_pct":-0.1077,"peak_pnl_pct":0.0897,"drawdown_from_peak":0.1974,"score_drop_from_peak":null}},"overheated":{"score":32,"warn":false,"crit":false,"details":{"rsi14":48.07912191041078,"move_2d_pct":-0.0864,"move_3d_pct":-0.1529,"move_3d_available":true}},"setup_erosion":{"score":0,"warn":false,"crit":false,"available":false,"reason":"no_entry_snapshot"},"catalyst":{"score":0,"warn":false,"crit":false,"details":{"earnings_date":"2026-08-06","trading_days_until":61,"window":2}},"trend_break":{"score":100,"warn":true,"crit":true,"details":{"ma21":1.8145,"price":1.74,"drop_pct":4.11}}},"peak_score_since_entry":null,"peak_pnl_pct_since_entry":0.0897,"current_score":null,"current_pnl_pct":-0.1077,"prev_exit_pressure":36,"computed_at":"2026-05-13T14:11:06Z"}},"DMRC":{"entry_date":"2026-05-11","entry_price":9.44,"shares":10,"entry_fx":0.8492,"fx_estimated":false,"entry_dtc":null,"entry_short_float":null,"entry_cost_to_borrow":null,"entry_snapshot_ts":null,"exit_state":{"exit_pressure":18,"triggers":{"score_decay":{"score":0,"warn":false,"crit":false,"available":false,"reason":"score_history zu kurz"},"profit_lock":{"score":0,"warn":false,"crit":false,"details":{"pnl_pct":-0.0487,"peak_pnl_pct":-0.0085,"drawdown_from_peak":null,"score_drop_from_peak":null}},"overheated":{"score":46,"warn":false,"crit":false,"details":{"rsi14":69.17143075704239,"move_2d_pct":0.0034,"move_3d_pct":-0.0406,"move_3d_available":true}},"setup_erosion":{"score":0,"warn":false,"crit":false,"available":false,"reason":"no_entry_snapshot"},"catalyst":{"score":0,"warn":false,"crit":false,"available":false,"reason":"kein Earnings-Datum aus Finnhub/yfinance"},"trend_break":{"score":0,"warn":false,"crit":false,"details":{"ma21":7.8302,"price":8.98,"drop_pct":-14.68}}},"peak_score_since_entry":null,"peak_pnl_pct_since_entry":-0.0085,"current_score":null,"current_pnl_pct":-0.0487,"prev_exit_pressure":18,"computed_at":"2026-05-13T14:11:06Z"}},"IONQ":{"entry_date":"2026-05-11","entry_price":49.1,"shares":40,"entry_fx":0.8485,"fx_estimated":false,"entry_dtc":null,"entry_short_float":null,"entry_cost_to_borrow":null,"entry_snapshot_ts":null,"exit_state":{"exit_pressure":28,"triggers":{"score_decay":{"score":0,"warn":false,"crit":false,"available":false,"reason":"score_history zu kurz"},"profit_lock":{"score":28,"warn":false,"crit":false,"details":{"pnl_pct":0.0955,"peak_pnl_pct":0.1788,"drawdown_from_peak":0.0833,"score_drop_from_peak":null}},"overheated":{"score":43,"warn":false,"crit":false,"details":{"rsi14":64.33179565475103,"move_2d_pct":-0.0552,"move_3d_pct":0.0916,"move_3d_available":true}},"setup_erosion":{"score":0,"warn":false,"crit":false,"available":false,"reason":"no_entry_snapshot"},"catalyst":{"score":0,"warn":false,"crit":false,"details":{"earnings_date":"2026-08-05","trading_days_until":60,"window":2}},"trend_break":{"score":0,"warn":false,"crit":false,"details":{"ma21":46.6405,"price":53.79,"drop_pct":-15.33}}},"peak_score_since_entry":null,"peak_pnl_pct_since_entry":0.1788,"current_score":null,"current_pnl_pct":0.0955,"prev_exit_pressure":23,"computed_at":"2026-05-13T14:11:06Z"}}},"push_history":[{"ts":"2026-05-09T20:58:08.006440+02:00","ticker":"NVAX","kind":"anomaly","severity":"high","trigger":"monster_backup","body":"NVAX \ud83d\udd25 Monster 95 | Setup 95 | KI 40","success":true},{"ts":"2026-05-09T22:52:54.877984+02:00","ticker":"GRPN","kind":"anomaly","severity":"medium","trigger":"score_jump","body":"GRPN \ud83d\ude80 Setup 88 \u2191 (gestern 62) | UOA Call/Put 11.5\u00d7","success":true},{"ts":"2026-05-10T04:43:55.177170+02:00","ticker":"NVAX","kind":"anomaly","severity":"high","trigger":"monster_backup","body":"NVAX \ud83d\udd25 Monster 100 | Setup 100 | KI 65","success":true},{"ts":"2026-05-10T08:10:20.027404+02:00","ticker":"GRPN","kind":"anomaly","severity":"medium","trigger":"score_jump","body":"GRPN \ud83d\ude80 Setup 88 \u2191 (gestern 62) | Volumen 3.0\u00d7 + \u26a1 Extremes Volumen 3.0\u00d7+ + Spanne 19.6% + UOA\u2026","success":true},{"ts":"2026-05-10T09:30:52.501915+02:00","ticker":"GRPN","kind":"anomaly","severity":"high","trigger":"monster_backup","body":"GRPN \ud83d\udd25 Monster 97 | Setup 97 | KI 55","success":true},{"ts":"2026-05-10T09:30:52.736745+02:00","ticker":"OFRM","kind":"anomaly","severity":"high","trigger":"monster_backup","body":"OFRM \ud83d\udd25 Monster 94 | Setup 78 | KI 55","success":true},{"ts":"2026-05-10T10:52:08.834374+02:00","ticker":"NVAX","kind":"anomaly","severity":"high","trigger":"monster_backup","body":"NVAX \ud83d\udd25 Monster 100 | Setup 100 | KI 65","success":true},{"ts":"2026-05-10T15:05:37.947343+02:00","ticker":"GRPN","kind":"anomaly","severity":"medium","trigger":"score_jump","body":"GRPN \ud83d\ude80 Setup 97 \u2191 (gestern 62) | Volumen 3.0\u00d7 + \u26a1 Extremes Volumen 3.0\u00d7+ + Spanne 19.6% + UOA\u2026","success":true},{"ts":"2026-05-10T16:51:01.063729+02:00","ticker":"GRPN","kind":"anomaly","severity":"high","trigger":"monster_backup","body":"GRPN \ud83d\udd25 Monster 97 | Setup 97 | KI 55","success":true},{"ts":"2026-05-10T17:51:47.058835+02:00","ticker":"NVAX","kind":"anomaly","severity":"high","trigger":"monster_backup","body":"NVAX \ud83d\udd25 Monster 100 | Setup 100 | KI 65","success":true},{"ts":"2026-05-10T18:53:05.781458+02:00","ticker":"OFRM","kind":"anomaly","severity":"high","trigger":"monster_backup","body":"OFRM \ud83d\udd25 Monster 94 | Setup 78 | KI 63","success":true},{"ts":"2026-05-10T22:02:17.181917+02:00","ticker":"GRPN","kind":"anomaly","severity":"medium","trigger":"score_jump","body":"GRPN \ud83d\ude80 Setup 97 \u2191 (gestern 62) | Volumen 3.0\u00d7 + \u26a1 Extremes Volumen 3.0\u00d7+ + Spanne 19.6% + UOA\u2026","success":true},{"ts":"2026-05-10T23:39:35.812340+02:00","ticker":"GRPN","kind":"anomaly","severity":"high","trigger":"monster_backup","body":"GRPN \ud83d\udd25 Monster 97 | Setup 97 | KI 63","success":true},{"ts":"2026-05-11T00:44:09.734890+02:00","ticker":"NVAX","kind":"anomaly","severity":"high","trigger":"monster_backup","body":"NVAX \ud83d\udd25 Monster 100 | Setup 100 | KI 65","success":true},{"ts":"2026-05-11T04:53:48.343158+02:00","ticker":"GRPN","kind":"anomaly","severity":"medium","trigger":"score_jump","body":"GRPN \ud83d\ude80 Setup 97 \u2191 (gestern 62) | Volumen 3.0\u00d7 + \u26a1 Extremes Volumen 3.0\u00d7+ + Spanne 19.6% + UOA\u2026","success":true},{"ts":"2026-05-11T08:38:43.628034+02:00","ticker":"NVAX","kind":"anomaly","severity":"high","trigger":"monster_backup","body":"NVAX \ud83d\udd25 Monster 100 | Setup 100 | KI 65","success":true},{"ts":"2026-05-11T08:38:43.742495+02:00","ticker":"GRPN","kind":"anomaly","severity":"high","trigger":"monster_backup","body":"GRPN \ud83d\udd25 Monster 97 | Setup 97 | KI 55","success":true},{"ts":"2026-05-11T12:37:11.234290+02:00","ticker":"GRPN","kind":"anomaly","severity":"medium","trigger":"score_jump","body":"GRPN \ud83d\ude80 Setup 97 \u2191 (gestern 62) | Volumen 3.0\u00d7 + \u26a1 Extremes Volumen 3.0\u00d7+ + Spanne 19.6% + UOA\u2026","success":true},{"ts":"2026-05-11T15:47:25.743017+02:00","ticker":"NVAX","kind":"anomaly","severity":"high","trigger":"monster_backup","body":"NVAX \ud83d\udd25 Monster 100 | Setup 100 | KI 50","success":true},{"ts":"2026-05-11T15:47:25.884712+02:00","ticker":"GRPN","kind":"anomaly","severity":"high","trigger":"monster_backup","body":"GRPN \ud83d\udd25 Monster 97 | Setup 97 | KI 20","success":true},{"ts":"2026-05-11T20:57:21.330145+02:00","ticker":"ENVX","kind":"anomaly","severity":"medium","trigger":"score_jump","body":"ENVX \ud83d\ude80 Setup 63 \u2191 (gestern 44) | Earnings in 2 Tagen (13.05.2026) + Volumen 1.6\u00d7 + Spanne 13.\u2026","success":true,"suppressed":false,"suppress_reason":null},{"ts":"2026-05-11T20:57:23.344359+02:00","ticker":"AMC","kind":"exit_p2","severity":"warning","trigger":null,"body":"\u26a0\ufe0f Exit-Warnung AMC: pressure 61/100","success":true,"suppressed":false,"suppress_reason":null},{"ts":"2026-05-11T20:57:23.522897+02:00","ticker":"AMC","kind":"exit_p2","severity":"trigger","trigger":"trend_break","body":"\ud83d\udd3b Exit-Signal AMC: trend_break crit ({'ma21': 1.5114, 'price': 1.435, 'drop_pct': 5.06})","success":true,"suppressed":false,"suppress_reason":null},{"ts":"2026-05-11T22:47:53.756857+02:00","ticker":"DFDV","kind":"anomaly","severity":"high","trigger":"monster_backup","body":"DFDV \ud83d\udd25 Monster 92 | Setup 77 | KI 82","success":true,"suppressed":false,"suppress_reason":null},{"ts":"2026-05-11T22:47:54.032620+02:00","ticker":"DMRC","kind":"earnings_immediate","severity":"default","trigger":null,"body":"DMRC Earnings-Sofort-Alert (in 1d, KI 66)","success":true,"suppressed":false,"suppress_reason":null},{"ts":"2026-05-12T00:05:53.036717+02:00","ticker":"DMRC","kind":"earnings_immediate","severity":"default","trigger":null,"body":"DMRC Earnings-Sofort-Alert (in 1d, KI 66)","success":true,"suppressed":false,"suppress_reason":null},{"ts":"2026-05-12T01:56:34.568452+02:00","ticker":"DMRC","kind":"earnings_immediate","severity":"default","trigger":null,"body":"DMRC Earnings-Sofort-Alert (in 1d, KI 53)","success":true,"suppressed":false,"suppress_reason":null},{"ts":"2026-05-12T04:57:18.126937+02:00","ticker":"ENVX","kind":"anomaly","severity":"medium","trigger":"score_jump","body":"ENVX \ud83d\ude80 Setup 72 \u2191 (gestern 44) | Earnings in 2 Tagen (13.05.2026) + Volumen 2.0\u00d7 + Spanne 13.\u2026","success":true,"suppressed":false,"suppress_reason":null},{"ts":"2026-05-12T08:16:37.443088+02:00","ticker":"DFDV","kind":"anomaly","severity":"high","trigger":"monster_backup","body":"DFDV \ud83d\udd25 Monster 93 | Setup 78 | KI 68","success":true,"suppressed":false,"suppress_reason":null},{"ts":"2026-05-12T08:16:37.513682+02:00","ticker":"ENVX","kind":"anomaly","severity":"high","trigger":"monster_backup","body":"ENVX \ud83d\udd25 Monster 93 | Setup 78 | KI 66","success":true,"suppressed":false,"suppress_reason":null},{"ts":"2026-05-12T08:16:46.397320+02:00","ticker":"DMRC","kind":"exit_p2","severity":"trigger","trigger":"catalyst","body":"\ud83d\udd3b Exit-Signal DMRC: catalyst crit ({'earnings_date': '2026-05-12', 'trading_days_until': 0, 'window': 2})","success":true,"suppressed":false,"suppress_reason":null},{"ts":"2026-05-12T11:36:37.993151+02:00","ticker":"ENVX","kind":"anomaly","severity":"medium","trigger":"score_jump","body":"ENVX \ud83d\ude80 Setup 78 \u2191 (gestern 44) | Earnings in 1 Tagen (13.05.2026) + Volumen 2.0\u00d7 + Spanne 13.\u2026","success":true,"suppressed":false,"suppress_reason":null},{"ts":"2026-05-12T11:36:46.134240+02:00","ticker":"AMC","kind":"exit_p2","severity":"warning","trigger":null,"body":"\u26a0\ufe0f Exit-Warnung AMC: pressure 64/100","success":true,"suppressed":false,"suppress_reason":null},{"ts":"2026-05-12T16:19:41.504021+02:00","ticker":"ENVX","kind":"anomaly","severity":"high","trigger":"monster_backup","body":"ENVX \ud83d\udd25 Monster 92 | Setup 77 | KI 25","success":true,"suppressed":false,"suppress_reason":null},{"ts":"2026-05-12T19:09:35.655880+02:00","ticker":"AMC","kind":"exit_p2","severity":"trigger","trigger":"profit_lock","body":"\ud83d\udd3b Exit-Signal AMC: profit_lock crit ({'pnl_pct': -0.0967, 'peak_pnl_pct': 0.16, 'drawdown_from_peak': 0.2567, 'score_drop_from_peak': None})","success":true,"suppressed":false,"suppress_reason":null},{"ts":"2026-05-12T20:19:24.529672+02:00","ticker":"WEN","kind":"anomaly","severity":"high","trigger":"monster_backup","body":"WEN \ud83d\udd25 Monster 100 | Setup 97 | KI 77","success":true,"suppressed":false,"suppress_reason":null},{"ts":"2026-05-12T20:19:24.801701+02:00","ticker":"RIGL","kind":"anomaly","severity":"medium","trigger":"score_jump","body":"RIGL \ud83d\ude80 Setup 78 \u2191 (gestern 40) | Volumen 1.7\u00d7 + Spanne 11.6% + News: short interest","success":true,"suppressed":false,"suppress_reason":null},{"ts":"2026-05-12T21:48:10.078812+02:00","ticker":"AMC","kind":"exit_p2","severity":"trigger","trigger":"trend_break","body":"\ud83d\udd3b Exit-Signal AMC: trend_break crit ({'ma21': 1.4965, 'price': 1.36, 'drop_pct': 9.12})","success":true,"suppressed":false,"suppress_reason":null,"conviction_score":null},{"ts":"2026-05-13T00:58:50.262662+02:00","ticker":"AMC","kind":"exit_p2","severity":"warning","trigger":null,"body":"\u26a0\ufe0f Exit-Warnung AMC: pressure 71/100","success":true,"suppressed":false,"suppress_reason":null,"conviction_score":null},{"ts":"2026-05-13T15:09:53.093370+02:00","ticker":"METC","kind":"anomaly","severity":"high","trigger":"monster_backup","body":"METC \ud83d\udd25 Monster 100 | Setup 100 | KI 55","success":false,"suppressed":true,"suppress_reason":"conviction_below_threshold","conviction_score":44},{"ts":"2026-05-13T15:09:53.093678+02:00","ticker":"WEN","kind":"anomaly","severity":"high","trigger":"monster_backup","body":"WEN \ud83d\udd25 Monster 100 | Setup 100 | KI 94","success":false,"suppressed":true,"suppress_reason":"conviction_below_threshold","conviction_score":58},{"ts":"2026-05-13T15:09:53.093898+02:00","ticker":"RIGL","kind":"anomaly","severity":"high","trigger":"monster_backup","body":"RIGL \ud83d\udd25 Monster 100 | Setup 95 | KI 61","success":false,"suppressed":true,"suppress_reason":"conviction_below_threshold","conviction_score":62},{"ts":"2026-05-13T15:09:53.093959+02:00","ticker":"CGEM","kind":"anomaly","severity":"high","trigger":"monster_backup","body":"CGEM \ud83d\udd25 Monster 96 | Setup 80 | KI 72","success":false,"suppressed":true,"suppress_reason":"conviction_below_threshold","conviction_score":37},{"ts":"2026-05-13T15:10:02.724833+02:00","ticker":"AMC","kind":"exit_p2","severity":"warning","trigger":null,"body":"\u26a0\ufe0f Exit-Warnung AMC: pressure 71/100","success":true,"suppressed":false,"suppress_reason":null,"conviction_score":null}],"fx_usd_eur":0.8536,"fx_usd_eur_computed_at":"2026-05-13T14:10:02Z","generated_at":"2026-05-13T16:17:27Z","vix_current":18.08,"run_phase":"postclose"}