{
  "consecutive_failures": {
    "finra": 0,
    "yfinance_singletons": 0,
    "stocktwits": 81,
    "uoa": 0,
    "news_rss": 0,
    "edgar_8k": 0,
    "edgar_form4": 0,
    "edgar_13d_g": 0,
    "yahoo_screener": 0,
    "earningswhispers": 41,
    "yfinance_batch": 0,
    "finviz": 60,
    "finnhub": 6,
    "stockanalysis": 0
  },
  "last_seen": {
    "finra": "2026-05-20T08:36:18Z",
    "yfinance_singletons": "2026-05-20T08:36:27Z",
    "stocktwits": "2026-05-18T19:04:11Z",
    "uoa": "2026-05-20T08:36:34Z",
    "news_rss": "2026-05-20T08:36:34Z",
    "edgar_8k": "2026-05-20T08:36:34Z",
    "edgar_form4": "2026-05-20T08:36:34Z",
    "edgar_13d_g": "2026-05-20T08:36:34Z",
    "yahoo_screener": "2026-05-20T04:06:57Z",
    "earningswhispers": "2026-05-18T18:58:45Z",
    "yfinance_batch": "2026-05-20T04:07:09Z",
    "finviz": "2026-05-20T04:08:04Z",
    "finnhub": "2026-05-16T08:25:06Z",
    "stockanalysis": "2026-05-20T04:08:04Z"
  },
  "last_digest_sent": "2026-05-20",
  "last_successful_run": null
}
