{
  "SPIR": [
    {
      "date": "08.04.2026",
      "score": 57.64
    }
  ],
  "SNBR": [
    {
      "date": "08.04.2026",
      "score": 54.85
    }
  ],
  "ELPW": [
    {
      "date": "08.04.2026",
      "score": 52.17
    }
  ],
  "EVTL": [
    {
      "date": "08.04.2026",
      "score": 38.29
    }
  ],
  "ALGT": [
    {
      "date": "08.04.2026",
      "score": 31.63
    }
  ],
  "APLD": [
    {
      "date": "08.04.2026",
      "score": 29.61
    }
  ],
  "WULF": [
    {
      "date": "08.04.2026",
      "score": 25.61
    }
  ],
  "TDUP": [
    {
      "date": "08.04.2026",
      "score": 25.24
    }
  ],
  "RR": [
    {
      "date": "08.04.2026",
      "score": 24.73
    }
  ],
  "FOSL": [
    {
      "date": "08.04.2026",
      "score": 23.62
    }
  ]
}