{
  "NMAX": [
    {
      "date": "16.04.2026",
      "score": 60.23
    }
  ],
  "PLCE": [
    {
      "date": "16.04.2026",
      "score": 52.63
    }
  ],
  "TTEC": [
    {
      "date": "16.04.2026",
      "score": 52.05
    }
  ],
  "WEED.TO": [
    {
      "date": "16.04.2026",
      "score": 49.94
    }
  ],
  "SOUN": [
    {
      "date": "16.04.2026",
      "score": 49.23
    }
  ],
  "REPL": [
    {
      "date": "16.04.2026",
      "score": 48.05
    }
  ],
  "CRON.TO": [
    {
      "date": "16.04.2026",
      "score": 47.18
    }
  ],
  "BIRD": [
    {
      "date": "16.04.2026",
      "score": 45.26
    }
  ],
  "SKLZ": [
    {
      "date": "16.04.2026",
      "score": 43.67
    }
  ],
  "RHI": [
    {
      "date": "16.04.2026",
      "score": 43.14
    }
  ]
}