{
  "GRPN": [
    [
      "29.04.2026",
      62.11
    ],
    [
      "30.04.2026",
      60.7
    ],
    [
      "12.05.2026",
      66.84
    ],
    [
      "13.05.2026",
      65.16
    ]
  ],
  "INDI": [
    [
      "29.04.2026",
      73.39
    ],
    [
      "30.04.2026",
      80.23
    ]
  ],
  "XRX": [
    [
      "29.04.2026",
      40.69
    ],
    [
      "30.04.2026",
      88.96
    ]
  ],
  "AVTX": [
    [
      "29.04.2026",
      36.51
    ]
  ],
  "AMC": [
    [
      "29.04.2026",
      16.14
    ],
    [
      "30.04.2026",
      19.03
    ]
  ],
  "PRLD": [
    [
      "30.04.2026",
      54.67
    ]
  ],
  "SNSE": [
    [
      "29.04.2026",
      55.33
    ],
    [
      "30.04.2026",
      52.7
    ],
    [
      "12.05.2026",
      61.43
    ],
    [
      "13.05.2026",
      54.47
    ]
  ],
  "NTLA": [
    [
      "29.04.2026",
      79.53
    ],
    [
      "30.04.2026",
      76.38
    ]
  ],
  "KALV": [
    [
      "29.04.2026",
      100.0
    ],
    [
      "30.04.2026",
      100.0
    ]
  ],
  "RXRX": [
    [
      "29.04.2026",
      49.63
    ],
    [
      "30.04.2026",
      64.51
    ]
  ],
  "SPRY": [
    [
      "29.04.2026",
      58.24
    ]
  ],
  "PCT": [
    [
      "29.04.2026",
      60.92
    ],
    [
      "30.04.2026",
      70.98
    ]
  ],
  "ENVX": [
    [
      "29.04.2026",
      44.02
    ],
    [
      "30.04.2026",
      44.02
    ],
    [
      "13.05.2026",
      64.48
    ]
  ],
  "JACK": [
    [
      "12.05.2026",
      51.23
    ]
  ],
  "ARCT": [
    [
      "29.04.2026",
      70.37
    ],
    [
      "30.04.2026",
      54.14
    ]
  ],
  "SKLZ": [
    [
      "30.04.2026",
      85.61
    ]
  ],
  "ACDC": [
    [
      "29.04.2026",
      47.35
    ],
    [
      "30.04.2026",
      48.23
    ]
  ],
  "CWH": [
    [
      "29.04.2026",
      18.48
    ],
    [
      "30.04.2026",
      57.5
    ]
  ],
  "VITL": [
    [
      "30.04.2026",
      63.41
    ]
  ],
  "CBRL": [
    [
      "29.04.2026",
      43.43
    ],
    [
      "30.04.2026",
      47.33
    ]
  ],
  "LENZ": [
    [
      "29.04.2026",
      51.97
    ],
    [
      "30.04.2026",
      56.8
    ]
  ],
  "FTRE": [
    [
      "30.04.2026",
      60.31
    ]
  ],
  "SNBR": [
    [
      "29.04.2026",
      41.44
    ],
    [
      "30.04.2026",
      33.73
    ]
  ],
  "LGIH": [
    [
      "29.04.2026",
      73.18
    ]
  ],
  "RIGL": [
    [
      "12.05.2026",
      86.48
    ],
    [
      "13.05.2026",
      71.24
    ]
  ],
  "BBAI": [
    [
      "29.04.2026",
      62.05
    ]
  ],
  "CSIQ": [
    [
      "29.04.2026",
      50.36
    ],
    [
      "13.05.2026",
      48.78
    ]
  ],
  "MNPR": [
    [
      "29.04.2026",
      55.45
    ],
    [
      "30.04.2026",
      57.33
    ]
  ],
  "SKYQ": [
    [
      "29.04.2026",
      54.44
    ],
    [
      "30.04.2026",
      56.96
    ]
  ],
  "PRTA": [
    [
      "29.04.2026",
      52.27
    ]
  ],
  "COUR": [
    [
      "29.04.2026",
      47.52
    ]
  ],
  "ABEO": [
    [
      "29.04.2026",
      43.72
    ]
  ],
  "AIXI": [
    [
      "29.04.2026",
      41.99
    ]
  ],
  "PEB": [
    [
      "29.04.2026",
      61.9
    ]
  ],
  "CLVT": [
    [
      "29.04.2026",
      59.13
    ],
    [
      "30.04.2026",
      65.93
    ]
  ],
  "TRIP": [
    [
      "29.04.2026",
      35.85
    ],
    [
      "30.04.2026",
      39.27
    ]
  ],
  "AI": [
    [
      "29.04.2026",
      34.49
    ]
  ],
  "GCTK": [
    [
      "29.04.2026",
      70.21
    ]
  ],
  "IQ": [
    [
      "29.04.2026",
      44.73
    ]
  ],
  "NAVI": [
    [
      "29.04.2026",
      67.75
    ]
  ],
  "FIP": [
    [
      "30.04.2026",
      81.36
    ]
  ],
  "PRKS": [
    [
      "30.04.2026",
      65.26
    ]
  ],
  "QURE": [
    [
      "30.04.2026",
      65.13
    ],
    [
      "12.05.2026",
      50.89
    ],
    [
      "13.05.2026",
      52.44
    ]
  ],
  "SVRA": [
    [
      "30.04.2026",
      50.47
    ]
  ],
  "WEN": [
    [
      "12.05.2026",
      88.07
    ],
    [
      "13.05.2026",
      90.07
    ]
  ],
  "DDD": [
    [
      "12.05.2026",
      85.8
    ],
    [
      "13.05.2026",
      50.51
    ]
  ],
  "METC": [
    [
      "12.05.2026",
      90.73
    ],
    [
      "13.05.2026",
      94.29
    ]
  ],
  "FABC": [
    [
      "12.05.2026",
      75.29
    ]
  ],
  "AEVA": [
    [
      "12.05.2026",
      75.88
    ],
    [
      "13.05.2026",
      63.3
    ]
  ],
  "NVAX": [
    [
      "12.05.2026",
      58.85
    ]
  ],
  "XPOF": [
    [
      "12.05.2026",
      55.8
    ]
  ],
  "GO": [
    [
      "12.05.2026",
      53.73
    ],
    [
      "13.05.2026",
      46.42
    ]
  ],
  "REPL": [
    [
      "12.05.2026",
      54.13
    ],
    [
      "13.05.2026",
      74.24
    ]
  ],
  "CGEM": [
    [
      "12.05.2026",
      69.05
    ],
    [
      "13.05.2026",
      72.85
    ]
  ],
  "ENOV": [
    [
      "12.05.2026",
      57.48
    ],
    [
      "13.05.2026",
      64.57
    ]
  ],
  "RXT": [
    [
      "12.05.2026",
      54.08
    ],
    [
      "13.05.2026",
      54.93
    ]
  ],
  "NVRI": [
    [
      "12.05.2026",
      47.45
    ],
    [
      "13.05.2026",
      50.29
    ]
  ],
  "SLS": [
    [
      "13.05.2026",
      86.9
    ]
  ],
  "HUMA": [
    [
      "13.05.2026",
      75.08
    ]
  ],
  "CCCC": [
    [
      "13.05.2026",
      78.74
    ]
  ],
  "TTEC": [
    [
      "13.05.2026",
      62.86
    ]
  ],
  "DMRC": [
    [
      "13.05.2026",
      88.63
    ]
  ],
  "WBTN": [
    [
      "13.05.2026",
      83.06
    ]
  ],
  "RR": [
    [
      "13.05.2026",
      65.04
    ]
  ],
  "SEAT": [
    [
      "13.05.2026",
      57.39
    ]
  ]
}